django_polars/__init__.py
django_polars/io.py
django_polars-0.2.0.dist-info/METADATA
django_polars-0.2.0.dist-info/WHEEL
django_polars-0.2.0.dist-info/licenses/LICENSE
django_polars-0.2.0.dist-info/RECORD
