Metadata-Version: 2.3
Name: django-polars
Version: 0.2.0
Summary: High performance dataframes with Django ORM integration.
Project-URL: Repository, https://github.com/flango-dev/django-polars
Project-URL: Documentation, https://github.com/flango-dev/django-polars/blob/main/README.md
Project-URL: Changelog, https://github.com/flango-dev/django-polars/blob/main/CHANGELOG.md
Author-email: Florian Kromer <kromer-florian@protonmail.com>
License: MIT License
License-File: LICENSE
Classifier: Development Status :: 4 - Beta
Classifier: Framework :: Django
Classifier: Intended Audience :: Developers
Classifier: License :: OSI Approved :: MIT License
Classifier: Operating System :: OS Independent
Classifier: Programming Language :: Python
Classifier: Programming Language :: Python :: 3.12
Requires-Python: >=3.12
Requires-Dist: polars>=0.20.31
